<?xml version="1.0" encoding="utf-8"?>
<!DOCTYPE hibernate-mapping PUBLIC "-//Hibernate/Hibernate Mapping DTD 3.0//EN"
"http://hibernate.sourceforge.net/hibernate-mapping-3.0.dtd">
<!-- 
    Mapping file autogenerated by MyEclipse Persistence Tools
-->
<hibernate-mapping>
    <class name="org.model.Amount" table="amount" catalog="nzj">
        <id name="id" type="java.lang.Long">
            <column name="id" />
            <generator class="identity" />
        </id>
        <property name="balance" type="java.lang.Double">
            <column name="balance" precision="20" not-null="true">
                <comment>余额</comment>
            </column>
        </property>
        <property name="userId" type="java.lang.Long">
            <column name="user_id" not-null="true" />
        </property>
    </class>
</hibernate-mapping>
